voxec/__init__.py
voxec/_voxec.pyd
voxec/voxec.py
voxec-0.4.2.dist-info/METADATA
voxec-0.4.2.dist-info/WHEEL
voxec-0.4.2.dist-info/top_level.txt
voxec-0.4.2.dist-info/RECORD
